{"metadata": {"dbt_schema_version": "https://schemas.getdbt.com/dbt/run-results/v6.json", "dbt_version": "1.11.8", "generated_at": "2026-04-27T18:19:45.522791Z", "invocation_id": "601ec48c-3d66-4b99-b38d-1f9419bf207b", "invocation_started_at": "2026-04-27T18:19:42.658593Z", "env": {}}, "results": [{"status": "success", "timing": [{"name": "compile", "started_at": "2026-04-27T18:19:44.141701Z", "completed_at": "2026-04-27T18:19:44.173209Z"}, {"name": "execute", "started_at": "2026-04-27T18:19:44.185284Z", "completed_at": "2026-04-27T18:19:44.549220Z"}], "thread_id": "Thread-1 (worker)", "execution_time": 0.44254589080810547, "adapter_response": {"_message": "SELECT 24", "code": "SELECT", "rows_affected": 24}, "message": "SELECT 24", "failures": null, "unique_id": "model.flight_dbt.dim_airline", "compiled": true, "compiled_code": "\nSELECT DISTINCT MD5(airline) AS airline_id,\n    airline\nFROM \"analytics_db\".\"public\".\"flight_prices_staging\"", "relation_name": "\"analytics_db\".\"public\".\"dim_airline\"", "batch_results": null}, {"status": "success", "timing": [{"name": "compile", "started_at": "2026-04-27T18:19:44.148113Z", "completed_at": "2026-04-27T18:19:44.230646Z"}, {"name": "execute", "started_at": "2026-04-27T18:19:44.238183Z", "completed_at": "2026-04-27T18:19:44.579566Z"}], "thread_id": "Thread-2 (worker)", "execution_time": 0.4666140079498291, "adapter_response": {"_message": "SELECT 152", "code": "SELECT", "rows_affected": 152}, "message": "SELECT 152", "failures": null, "unique_id": "model.flight_dbt.dim_route", "compiled": true, "compiled_code": "\nSELECT DISTINCT MD5(source || '-' || destination) AS route_id,\n    source,\n    destination\nFROM \"analytics_db\".\"public\".\"flight_prices_staging\"", "relation_name": "\"analytics_db\".\"public\".\"dim_route\"", "batch_results": null}, {"status": "success", "timing": [{"name": "compile", "started_at": "2026-04-27T18:19:44.152305Z", "completed_at": "2026-04-27T18:19:44.217461Z"}, {"name": "execute", "started_at": "2026-04-27T18:19:44.218232Z", "completed_at": "2026-04-27T18:19:44.585813Z"}], "thread_id": "Thread-3 (worker)", "execution_time": 0.46883273124694824, "adapter_response": {"_message": "SELECT 4", "code": "SELECT", "rows_affected": 4}, "message": "SELECT 4", "failures": null, "unique_id": "model.flight_dbt.dim_season", "compiled": true, "compiled_code": "\nSELECT DISTINCT MD5(seasonality) AS season_id,\n    seasonality\nFROM \"analytics_db\".\"public\".\"flight_prices_staging\"", "relation_name": "\"analytics_db\".\"public\".\"dim_season\"", "batch_results": null}, {"status": "success", "timing": [{"name": "compile", "started_at": "2026-04-27T18:19:44.123920Z", "completed_at": "2026-04-27T18:19:44.147358Z"}, {"name": "execute", "started_at": "2026-04-27T18:19:44.157179Z", "completed_at": "2026-04-27T18:19:44.886778Z"}], "thread_id": "Thread-4 (worker)", "execution_time": 0.773113489151001, "adapter_response": {"_message": "SELECT 57000", "code": "SELECT", "rows_affected": 57000}, "message": "SELECT 57000", "failures": null, "unique_id": "model.flight_dbt.staging_flights", "compiled": true, "compiled_code": " WITH deduplicated AS (\n    SELECT DISTINCT airline,\n        source,\n        source_name,\n        destination,\n        destination_name,\n        departure_time,\n        arrival_time,\n        duration,\n        stops,\n        aircraft_type,\n        class,\n        booking_source,\n        base_fare,\n        tax_and_surcharge,\n        total_fare,\n        seasonality\n    FROM \"analytics_db\".\"public\".\"flight_prices_staging\"\n)\nSELECT MD5(\n        COALESCE(airline, '') || '|' || COALESCE(source, '') || '|' || COALESCE(destination, '') || '|' || COALESCE(CAST(departure_time AS VARCHAR), '') || '|' || COALESCE(CAST(total_fare AS VARCHAR), '')\n    ) AS flight_id,\n    airline,\n    source,\n    source_name,\n    destination,\n    destination_name,\n    departure_time,\n    arrival_time,\n    duration,\n    stops,\n    aircraft_type,\n    class,\n    booking_source,\n    base_fare,\n    tax_and_surcharge,\n    total_fare,\n    seasonality,\n    CURRENT_TIMESTAMP AS loaded_at\nFROM deduplicated", "relation_name": "\"analytics_db\".\"public\".\"staging_flights\"", "batch_results": null}, {"status": "success", "timing": [{"name": "compile", "started_at": "2026-04-27T18:19:44.895411Z", "completed_at": "2026-04-27T18:19:44.900044Z"}, {"name": "execute", "started_at": "2026-04-27T18:19:44.900718Z", "completed_at": "2026-04-27T18:19:45.318085Z"}], "thread_id": "Thread-1 (worker)", "execution_time": 0.42526841163635254, "adapter_response": {"_message": "SELECT 57000", "code": "SELECT", "rows_affected": 57000}, "message": "SELECT 57000", "failures": null, "unique_id": "model.flight_dbt.fact_flight_prices", "compiled": true, "compiled_code": "\nSELECT MD5(COALESCE(airline, '')) AS airline_id,\n    MD5(\n        COALESCE(source, '') || '|' || COALESCE(destination, '')\n    ) AS route_id,\n    MD5(COALESCE(seasonality, '')) AS season_id,\n    flight_id,\n    airline,\n    source,\n    destination,\n    departure_time,\n    arrival_time,\n    duration,\n    stops,\n    aircraft_type,\n    class,\n    booking_source,\n    base_fare,\n    tax_and_surcharge,\n    total_fare,\n    seasonality,\n    loaded_at\nFROM \"analytics_db\".\"public\".\"staging_flights\"", "relation_name": "\"analytics_db\".\"public\".\"fact_flight_prices\"", "batch_results": null}, {"status": "success", "timing": [{"name": "compile", "started_at": "2026-04-27T18:19:45.328691Z", "completed_at": "2026-04-27T18:19:45.334200Z"}, {"name": "execute", "started_at": "2026-04-27T18:19:45.335159Z", "completed_at": "2026-04-27T18:19:45.495934Z"}], "thread_id": "Thread-2 (worker)", "execution_time": 0.17049717903137207, "adapter_response": {"_message": "SELECT 8456", "code": "SELECT", "rows_affected": 8456}, "message": "SELECT 8456", "failures": null, "unique_id": "model.flight_dbt.fact_kpis", "compiled": true, "compiled_code": " WITH route_counts AS (\n    SELECT route_id,\n        COUNT(*) AS route_count\n    FROM \"analytics_db\".\"public\".\"fact_flight_prices\"\n    GROUP BY route_id\n)\nSELECT f.airline_id,\n    f.route_id,\n    f.season_id,\n    AVG(f.total_fare) AS avg_fare,\n    COUNT(*) AS booking_count,\n    COALESCE(rc.route_count, 0) AS route_count\nFROM \"analytics_db\".\"public\".\"fact_flight_prices\" f\n    LEFT JOIN route_counts rc ON f.route_id = rc.route_id\nGROUP BY f.airline_id,\n    f.route_id,\n    f.season_id,\n    rc.route_count", "relation_name": "\"analytics_db\".\"public\".\"fact_kpis\"", "batch_results": null}], "elapsed_time": 1.6255860328674316, "args": {"log_format": "default", "macro_debugging": false, "require_resource_names_without_spaces": true, "partial_parse": true, "sqlparse": {"MAX_GROUPING_DEPTH": null, "MAX_GROUPING_TOKENS": null}, "require_explicit_package_overrides_for_builtin_materializations": true, "skip_nodes_if_on_run_start_fails": false, "require_batched_execution_for_custom_microbatch_strategy": false, "which": "run", "send_anonymous_usage_stats": true, "validate_macro_args": false, "warn_error_options": {"error": [], "warn": [], "silence": []}, "static_parser": true, "vars": {}, "defer": false, "exclude": [], "favor_state": false, "indirect_selection": "eager", "show_resource_report": false, "use_colors": true, "use_fast_test_edges": false, "populate_cache": true, "log_file_max_bytes": 10485760, "log_level": "debug", "cache_selected_only": false, "quiet": false, "partial_parse_file_diff": true, "require_all_warnings_handled_by_warn_error": false, "require_generic_test_arguments_property": true, "print": true, "select": [], "state_modified_compare_vars": false, "version_check": true, "write_json": true, "require_yaml_configuration_for_mf_time_spines": false, "profiles_dir": "/opt/airflow/dbt", "log_path": "/opt/airflow/dbt/logs", "printer_width": 80, "project_dir": "/opt/airflow/dbt", "use_colors_file": true, "strict_mode": false, "invocation_command": "dbt run --project-dir /opt/airflow/dbt --profiles-dir /opt/airflow/dbt --log-level debug", "empty": false, "upload_to_artifacts_ingest_api": false, "log_level_file": "debug", "source_freshness_run_project_hooks": true, "require_nested_cumulative_type_params": false, "introspect": true, "show_all_deprecations": false, "state_modified_compare_more_unrendered_values": false, "require_ref_searches_node_package_before_root": false, "require_unique_project_resource_names": false, "log_format_file": "debug"}}